origin_Yzb_regret.py
setup.py
origin_Yzb_regret.egg-info/PKG-INFO
origin_Yzb_regret.egg-info/SOURCES.txt
origin_Yzb_regret.egg-info/dependency_links.txt
origin_Yzb_regret.egg-info/entry_points.txt
origin_Yzb_regret.egg-info/top_level.txt