Metadata-Version: 1.2
Name: origin-Yzb-regret
Version: 0.1.0
Summary: My Script description
Home-page: https://github.com/your_username/origin_Yzb_regret
Author: Yzb_regret
Author-email: 2646332343@qq.com
License: UNKNOWN
Platform: UNKNOWN
Requires-Python: >=3.6
